PyLogger/Logger.py
PyLogger/__init__.py
PyLogger/constants.py
PyLogger/handlers.py
SimplePyLogger-0.3.0.dist-info/METADATA
SimplePyLogger-0.3.0.dist-info/WHEEL
SimplePyLogger-0.3.0.dist-info/top_level.txt
SimplePyLogger-0.3.0.dist-info/RECORD
