Metadata-Version: 2.1
Name: SimplePyLogger
Version: 0.3.0
Summary: Simple Python logger.
Home-page: https://github.com/lucas-meira/Logger
Author: Lucas Meira
Author-email: lima07.lucas@gmail.com
License: UNKNOWN
Project-URL: Source, https://github.com/lucas-meira/PyLogger
Platform: UNKNOWN
Classifier: Operating System :: OS Independent
Classifier: Programming Language :: Python
Classifier: Topic :: Software Development
Requires-Python: >=3.6
Requires-Dist: colorama
